gunzip/__init__.py
gunzip-0.1.10.dist-info/LICENSE
gunzip-0.1.10.dist-info/METADATA
gunzip-0.1.10.dist-info/WHEEL
gunzip-0.1.10.dist-info/entry_points.txt
gunzip-0.1.10.dist-info/top_level.txt
gunzip-0.1.10.dist-info/RECORD
